[
    {
        "__id": 73181,
        "shape_id": "510014",
        "shape_lat": "41.501235",
        "shape_lon": "-81.692485",
        "shape_sequence": "10001"
    },
    {
        "__id": 73182,
        "shape_id": "510014",
        "shape_lat": "41.501220",
        "shape_lon": "-81.692513",
        "shape_sequence": "10002"
    },
    {
        "__id": 73183,
        "shape_id": "510014",
        "shape_lat": "41.500857",
        "shape_lon": "-81.692199",
        "shape_sequence": "10003"
    },
    {
        "__id": 73184,
        "shape_id": "510014",
        "shape_lat": "41.500595",
        "shape_lon": "-81.691977",
        "shape_sequence": "10004"
    },
    {
        "__id": 73185,
        "shape_id": "510014",
        "shape_lat": "41.500543",
        "shape_lon": "-81.691932",
        "shape_sequence": "10005"
    },
    {
        "__id": 73186,
        "shape_id": "510014",
        "shape_lat": "41.500218",
        "shape_lon": "-81.692552",
        "shape_sequence": "10006"
    },
    {
        "__id": 73187,
        "shape_id": "510014",
        "shape_lat": "41.500181",
        "shape_lon": "-81.692618",
        "shape_sequence": "10007"
    },
    {
        "__id": 73188,
        "shape_id": "510014",
        "shape_lat": "41.500181",
        "shape_lon": "-81.692618",
        "shape_sequence": "20001"
    },
    {
        "__id": 73189,
        "shape_id": "510014",
        "shape_lat": "41.500161",
        "shape_lon": "-81.692655",
        "shape_sequence": "20002"
    },
    {
        "__id": 73190,
        "shape_id": "510014",
        "shape_lat": "41.500051",
        "shape_lon": "-81.692871",
        "shape_sequence": "20003"
    },
    {
        "__id": 73191,
        "shape_id": "510014",
        "shape_lat": "41.499648",
        "shape_lon": "-81.693674",
        "shape_sequence": "20004"
    },
    {
        "__id": 73192,
        "shape_id": "510014",
        "shape_lat": "41.499446",
        "shape_lon": "-81.694074",
        "shape_sequence": "20005"
    },
    {
        "__id": 73193,
        "shape_id": "510014",
        "shape_lat": "41.499236",
        "shape_lon": "-81.694477",
        "shape_sequence": "20006"
    },
    {
        "__id": 73194,
        "shape_id": "510014",
        "shape_lat": "41.498966",
        "shape_lon": "-81.695002",
        "shape_sequence": "20007"
    },
    {
        "__id": 73195,
        "shape_id": "510014",
        "shape_lat": "41.498859",
        "shape_lon": "-81.695208",
        "shape_sequence": "20008"
    },
    {
        "__id": 73196,
        "shape_id": "510014",
        "shape_lat": "41.498859",
        "shape_lon": "-81.695208",
        "shape_sequence": "30001"
    },
    {
        "__id": 73197,
        "shape_id": "510014",
        "shape_lat": "41.498743",
        "shape_lon": "-81.695431",
        "shape_sequence": "30002"
    },
    {
        "__id": 73198,
        "shape_id": "510014",
        "shape_lat": "41.498212",
        "shape_lon": "-81.696480",
        "shape_sequence": "30003"
    },
    {
        "__id": 73199,
        "shape_id": "510014",
        "shape_lat": "41.497969",
        "shape_lon": "-81.696999",
        "shape_sequence": "30004"
    },
    {
        "__id": 73200,
        "shape_id": "510014",
        "shape_lat": "41.497742",
        "shape_lon": "-81.697448",
        "shape_sequence": "30005"
    },
    {
        "__id": 73201,
        "shape_id": "510014",
        "shape_lat": "41.497628",
        "shape_lon": "-81.697685",
        "shape_sequence": "30006"
    },
    {
        "__id": 73202,
        "shape_id": "510014",
        "shape_lat": "41.497445",
        "shape_lon": "-81.698033",
        "shape_sequence": "30007"
    },
    {
        "__id": 73203,
        "shape_id": "510014",
        "shape_lat": "41.497358",
        "shape_lon": "-81.698183",
        "shape_sequence": "30008"
    },
    {
        "__id": 73204,
        "shape_id": "510014",
        "shape_lat": "41.497293",
        "shape_lon": "-81.698302",
        "shape_sequence": "30009"
    },
    {
        "__id": 73205,
        "shape_id": "510014",
        "shape_lat": "41.497213",
        "shape_lon": "-81.698420",
        "shape_sequence": "30010"
    },
    {
        "__id": 73206,
        "shape_id": "510014",
        "shape_lat": "41.497152",
        "shape_lon": "-81.698520",
        "shape_sequence": "30011"
    },
    {
        "__id": 73207,
        "shape_id": "510014",
        "shape_lat": "41.497073",
        "shape_lon": "-81.698656",
        "shape_sequence": "30012"
    },
    {
        "__id": 73208,
        "shape_id": "510014",
        "shape_lat": "41.496902",
        "shape_lon": "-81.698927",
        "shape_sequence": "30013"
    },
    {
        "__id": 73209,
        "shape_id": "510014",
        "shape_lat": "41.496342",
        "shape_lon": "-81.699724",
        "shape_sequence": "30014"
    },
    {
        "__id": 73210,
        "shape_id": "510014",
        "shape_lat": "41.496256",
        "shape_lon": "-81.699857",
        "shape_sequence": "30015"
    },
    {
        "__id": 73211,
        "shape_id": "510014",
        "shape_lat": "41.496048",
        "shape_lon": "-81.700160",
        "shape_sequence": "30016"
    },
    {
        "__id": 73212,
        "shape_id": "510014",
        "shape_lat": "41.495969",
        "shape_lon": "-81.700267",
        "shape_sequence": "30017"
    },
    {
        "__id": 73213,
        "shape_id": "510014",
        "shape_lat": "41.495936",
        "shape_lon": "-81.700315",
        "shape_sequence": "30018"
    },
    {
        "__id": 73214,
        "shape_id": "510014",
        "shape_lat": "41.495372",
        "shape_lon": "-81.701103",
        "shape_sequence": "30019"
    },
    {
        "__id": 73215,
        "shape_id": "510014",
        "shape_lat": "41.495056",
        "shape_lon": "-81.701562",
        "shape_sequence": "30020"
    },
    {
        "__id": 73216,
        "shape_id": "510014",
        "shape_lat": "41.494246",
        "shape_lon": "-81.702780",
        "shape_sequence": "30021"
    },
    {
        "__id": 73217,
        "shape_id": "510014",
        "shape_lat": "41.494191",
        "shape_lon": "-81.702877",
        "shape_sequence": "30022"
    },
    {
        "__id": 73218,
        "shape_id": "510014",
        "shape_lat": "41.493930",
        "shape_lon": "-81.703282",
        "shape_sequence": "30023"
    },
    {
        "__id": 73219,
        "shape_id": "510014",
        "shape_lat": "41.493278",
        "shape_lon": "-81.704213",
        "shape_sequence": "30024"
    },
    {
        "__id": 73220,
        "shape_id": "510014",
        "shape_lat": "41.492776",
        "shape_lon": "-81.704935",
        "shape_sequence": "30025"
    },
    {
        "__id": 73221,
        "shape_id": "510014",
        "shape_lat": "41.492719",
        "shape_lon": "-81.705021",
        "shape_sequence": "30026"
    },
    {
        "__id": 73222,
        "shape_id": "510014",
        "shape_lat": "41.492649",
        "shape_lon": "-81.705121",
        "shape_sequence": "30027"
    },
    {
        "__id": 73223,
        "shape_id": "510014",
        "shape_lat": "41.492399",
        "shape_lon": "-81.705472",
        "shape_sequence": "30028"
    },
    {
        "__id": 73224,
        "shape_id": "510014",
        "shape_lat": "41.492261",
        "shape_lon": "-81.705673",
        "shape_sequence": "30029"
    },
    {
        "__id": 73225,
        "shape_id": "510014",
        "shape_lat": "41.492204",
        "shape_lon": "-81.705754",
        "shape_sequence": "30030"
    },
    {
        "__id": 73226,
        "shape_id": "510014",
        "shape_lat": "41.492076",
        "shape_lon": "-81.705941",
        "shape_sequence": "30031"
    },
    {
        "__id": 73227,
        "shape_id": "510014",
        "shape_lat": "41.492032",
        "shape_lon": "-81.706018",
        "shape_sequence": "30032"
    },
    {
        "__id": 73228,
        "shape_id": "510014",
        "shape_lat": "41.491957",
        "shape_lon": "-81.706146",
        "shape_sequence": "30033"
    },
    {
        "__id": 73229,
        "shape_id": "510014",
        "shape_lat": "41.491923",
        "shape_lon": "-81.706211",
        "shape_sequence": "30034"
    },
    {
        "__id": 73230,
        "shape_id": "510014",
        "shape_lat": "41.491888",
        "shape_lon": "-81.706289",
        "shape_sequence": "30035"
    },
    {
        "__id": 73231,
        "shape_id": "510014",
        "shape_lat": "41.491850",
        "shape_lon": "-81.706376",
        "shape_sequence": "30036"
    },
    {
        "__id": 73232,
        "shape_id": "510014",
        "shape_lat": "41.491808",
        "shape_lon": "-81.706479",
        "shape_sequence": "30037"
    },
    {
        "__id": 73233,
        "shape_id": "510014",
        "shape_lat": "41.491721",
        "shape_lon": "-81.706689",
        "shape_sequence": "30038"
    },
    {
        "__id": 73234,
        "shape_id": "510014",
        "shape_lat": "41.491553",
        "shape_lon": "-81.707072",
        "shape_sequence": "30039"
    },
    {
        "__id": 73235,
        "shape_id": "510014",
        "shape_lat": "41.491419",
        "shape_lon": "-81.707394",
        "shape_sequence": "30040"
    },
    {
        "__id": 73236,
        "shape_id": "510014",
        "shape_lat": "41.491353",
        "shape_lon": "-81.707338",
        "shape_sequence": "30041"
    },
    {
        "__id": 73237,
        "shape_id": "510014",
        "shape_lat": "41.491304",
        "shape_lon": "-81.707301",
        "shape_sequence": "30042"
    },
    {
        "__id": 73238,
        "shape_id": "510014",
        "shape_lat": "41.491265",
        "shape_lon": "-81.707278",
        "shape_sequence": "30043"
    },
    {
        "__id": 73239,
        "shape_id": "510014",
        "shape_lat": "41.491226",
        "shape_lon": "-81.707260",
        "shape_sequence": "30044"
    },
    {
        "__id": 73240,
        "shape_id": "510014",
        "shape_lat": "41.491184",
        "shape_lon": "-81.707245",
        "shape_sequence": "30045"
    },
    {
        "__id": 73241,
        "shape_id": "510014",
        "shape_lat": "41.490825",
        "shape_lon": "-81.707138",
        "shape_sequence": "30046"
    },
    {
        "__id": 73242,
        "shape_id": "510014",
        "shape_lat": "41.490820",
        "shape_lon": "-81.707137",
        "shape_sequence": "30047"
    },
    {
        "__id": 73243,
        "shape_id": "510014",
        "shape_lat": "41.490820",
        "shape_lon": "-81.707137",
        "shape_sequence": "40001"
    },
    {
        "__id": 73244,
        "shape_id": "510014",
        "shape_lat": "41.490671",
        "shape_lon": "-81.707094",
        "shape_sequence": "40002"
    },
    {
        "__id": 73245,
        "shape_id": "510014",
        "shape_lat": "41.490016",
        "shape_lon": "-81.706893",
        "shape_sequence": "40003"
    },
    {
        "__id": 73246,
        "shape_id": "510014",
        "shape_lat": "41.489819",
        "shape_lon": "-81.706836",
        "shape_sequence": "40004"
    },
    {
        "__id": 73247,
        "shape_id": "510014",
        "shape_lat": "41.489553",
        "shape_lon": "-81.706761",
        "shape_sequence": "40005"
    },
    {
        "__id": 73248,
        "shape_id": "510014",
        "shape_lat": "41.489091",
        "shape_lon": "-81.706622",
        "shape_sequence": "40006"
    },
    {
        "__id": 73249,
        "shape_id": "510014",
        "shape_lat": "41.488758",
        "shape_lon": "-81.706522",
        "shape_sequence": "40007"
    },
    {
        "__id": 73250,
        "shape_id": "510014",
        "shape_lat": "41.488608",
        "shape_lon": "-81.706479",
        "shape_sequence": "40008"
    },
    {
        "__id": 73251,
        "shape_id": "510014",
        "shape_lat": "41.488608",
        "shape_lon": "-81.706479",
        "shape_sequence": "50001"
    },
    {
        "__id": 73252,
        "shape_id": "510014",
        "shape_lat": "41.488459",
        "shape_lon": "-81.706437",
        "shape_sequence": "50002"
    },
    {
        "__id": 73253,
        "shape_id": "510014",
        "shape_lat": "41.488406",
        "shape_lon": "-81.706421",
        "shape_sequence": "50003"
    },
    {
        "__id": 73254,
        "shape_id": "510014",
        "shape_lat": "41.488090",
        "shape_lon": "-81.706328",
        "shape_sequence": "50004"
    },
    {
        "__id": 73255,
        "shape_id": "510014",
        "shape_lat": "41.488053",
        "shape_lon": "-81.706315",
        "shape_sequence": "50005"
    },
    {
        "__id": 73256,
        "shape_id": "510014",
        "shape_lat": "41.487775",
        "shape_lon": "-81.706217",
        "shape_sequence": "50006"
    },
    {
        "__id": 73257,
        "shape_id": "510014",
        "shape_lat": "41.487698",
        "shape_lon": "-81.706175",
        "shape_sequence": "50007"
    },
    {
        "__id": 73258,
        "shape_id": "510014",
        "shape_lat": "41.487658",
        "shape_lon": "-81.706151",
        "shape_sequence": "50008"
    },
    {
        "__id": 73259,
        "shape_id": "510014",
        "shape_lat": "41.487605",
        "shape_lon": "-81.706118",
        "shape_sequence": "50009"
    },
    {
        "__id": 73260,
        "shape_id": "510014",
        "shape_lat": "41.487548",
        "shape_lon": "-81.706075",
        "shape_sequence": "50010"
    },
    {
        "__id": 73261,
        "shape_id": "510014",
        "shape_lat": "41.487243",
        "shape_lon": "-81.705834",
        "shape_sequence": "50011"
    },
    {
        "__id": 73262,
        "shape_id": "510014",
        "shape_lat": "41.487180",
        "shape_lon": "-81.705785",
        "shape_sequence": "50012"
    },
    {
        "__id": 73263,
        "shape_id": "510014",
        "shape_lat": "41.487041",
        "shape_lon": "-81.705672",
        "shape_sequence": "50013"
    },
    {
        "__id": 73264,
        "shape_id": "510014",
        "shape_lat": "41.486835",
        "shape_lon": "-81.705501",
        "shape_sequence": "50014"
    },
    {
        "__id": 73265,
        "shape_id": "510014",
        "shape_lat": "41.486835",
        "shape_lon": "-81.705501",
        "shape_sequence": "60001"
    },
    {
        "__id": 73266,
        "shape_id": "510014",
        "shape_lat": "41.486711",
        "shape_lon": "-81.705398",
        "shape_sequence": "60002"
    },
    {
        "__id": 73267,
        "shape_id": "510014",
        "shape_lat": "41.486618",
        "shape_lon": "-81.705318",
        "shape_sequence": "60003"
    },
    {
        "__id": 73268,
        "shape_id": "510014",
        "shape_lat": "41.486407",
        "shape_lon": "-81.705157",
        "shape_sequence": "60004"
    },
    {
        "__id": 73269,
        "shape_id": "510014",
        "shape_lat": "41.486278",
        "shape_lon": "-81.705055",
        "shape_sequence": "60005"
    },
    {
        "__id": 73270,
        "shape_id": "510014",
        "shape_lat": "41.486071",
        "shape_lon": "-81.704890",
        "shape_sequence": "60006"
    },
    {
        "__id": 73271,
        "shape_id": "510014",
        "shape_lat": "41.485925",
        "shape_lon": "-81.704779",
        "shape_sequence": "60007"
    },
    {
        "__id": 73272,
        "shape_id": "510014",
        "shape_lat": "41.485640",
        "shape_lon": "-81.704554",
        "shape_sequence": "60008"
    },
    {
        "__id": 73273,
        "shape_id": "510014",
        "shape_lat": "41.485257",
        "shape_lon": "-81.704247",
        "shape_sequence": "60009"
    },
    {
        "__id": 73274,
        "shape_id": "510014",
        "shape_lat": "41.484695",
        "shape_lon": "-81.703794",
        "shape_sequence": "60010"
    },
    {
        "__id": 73275,
        "shape_id": "510014",
        "shape_lat": "41.484576",
        "shape_lon": "-81.703700",
        "shape_sequence": "60011"
    },
    {
        "__id": 73276,
        "shape_id": "510014",
        "shape_lat": "41.484389",
        "shape_lon": "-81.703545",
        "shape_sequence": "60012"
    },
    {
        "__id": 73277,
        "shape_id": "510014",
        "shape_lat": "41.484389",
        "shape_lon": "-81.703545",
        "shape_sequence": "70001"
    },
    {
        "__id": 73278,
        "shape_id": "510014",
        "shape_lat": "41.484173",
        "shape_lon": "-81.703365",
        "shape_sequence": "70002"
    },
    {
        "__id": 73279,
        "shape_id": "510014",
        "shape_lat": "41.483773",
        "shape_lon": "-81.703048",
        "shape_sequence": "70003"
    },
    {
        "__id": 73280,
        "shape_id": "510014",
        "shape_lat": "41.483486",
        "shape_lon": "-81.702816",
        "shape_sequence": "70004"
    },
    {
        "__id": 73281,
        "shape_id": "510014",
        "shape_lat": "41.483142",
        "shape_lon": "-81.702539",
        "shape_sequence": "70005"
    },
    {
        "__id": 73282,
        "shape_id": "510014",
        "shape_lat": "41.482919",
        "shape_lon": "-81.702358",
        "shape_sequence": "70006"
    },
    {
        "__id": 73283,
        "shape_id": "510014",
        "shape_lat": "41.482919",
        "shape_lon": "-81.702358",
        "shape_sequence": "80001"
    },
    {
        "__id": 73284,
        "shape_id": "510014",
        "shape_lat": "41.482773",
        "shape_lon": "-81.702239",
        "shape_sequence": "80002"
    },
    {
        "__id": 73285,
        "shape_id": "510014",
        "shape_lat": "41.482732",
        "shape_lon": "-81.702205",
        "shape_sequence": "80003"
    },
    {
        "__id": 73286,
        "shape_id": "510014",
        "shape_lat": "41.482483",
        "shape_lon": "-81.702005",
        "shape_sequence": "80004"
    },
    {
        "__id": 73287,
        "shape_id": "510014",
        "shape_lat": "41.482370",
        "shape_lon": "-81.701915",
        "shape_sequence": "80005"
    },
    {
        "__id": 73288,
        "shape_id": "510014",
        "shape_lat": "41.481613",
        "shape_lon": "-81.701312",
        "shape_sequence": "80006"
    },
    {
        "__id": 73289,
        "shape_id": "510014",
        "shape_lat": "41.481467",
        "shape_lon": "-81.701172",
        "shape_sequence": "80007"
    },
    {
        "__id": 73290,
        "shape_id": "510014",
        "shape_lat": "41.481388",
        "shape_lon": "-81.701106",
        "shape_sequence": "80008"
    },
    {
        "__id": 73291,
        "shape_id": "510014",
        "shape_lat": "41.481234",
        "shape_lon": "-81.700987",
        "shape_sequence": "80009"
    },
    {
        "__id": 73292,
        "shape_id": "510014",
        "shape_lat": "41.481196",
        "shape_lon": "-81.700956",
        "shape_sequence": "80010"
    },
    {
        "__id": 73293,
        "shape_id": "510014",
        "shape_lat": "41.481196",
        "shape_lon": "-81.700956",
        "shape_sequence": "90001"
    },
    {
        "__id": 73294,
        "shape_id": "510014",
        "shape_lat": "41.481135",
        "shape_lon": "-81.700907",
        "shape_sequence": "90002"
    },
    {
        "__id": 73295,
        "shape_id": "510014",
        "shape_lat": "41.481067",
        "shape_lon": "-81.700862",
        "shape_sequence": "90003"
    },
    {
        "__id": 73296,
        "shape_id": "510014",
        "shape_lat": "41.480977",
        "shape_lon": "-81.700811",
        "shape_sequence": "90004"
    },
    {
        "__id": 73297,
        "shape_id": "510014",
        "shape_lat": "41.480818",
        "shape_lon": "-81.700716",
        "shape_sequence": "90005"
    },
    {
        "__id": 73298,
        "shape_id": "510014",
        "shape_lat": "41.480715",
        "shape_lon": "-81.700663",
        "shape_sequence": "90006"
    },
    {
        "__id": 73299,
        "shape_id": "510014",
        "shape_lat": "41.480417",
        "shape_lon": "-81.700521",
        "shape_sequence": "90007"
    },
    {
        "__id": 73300,
        "shape_id": "510014",
        "shape_lat": "41.479993",
        "shape_lon": "-81.700327",
        "shape_sequence": "90008"
    },
    {
        "__id": 73301,
        "shape_id": "510014",
        "shape_lat": "41.479578",
        "shape_lon": "-81.700122",
        "shape_sequence": "90009"
    },
    {
        "__id": 73302,
        "shape_id": "510014",
        "shape_lat": "41.478784",
        "shape_lon": "-81.699732",
        "shape_sequence": "90010"
    },
    {
        "__id": 73303,
        "shape_id": "510014",
        "shape_lat": "41.478532",
        "shape_lon": "-81.699604",
        "shape_sequence": "90011"
    },
    {
        "__id": 73304,
        "shape_id": "510014",
        "shape_lat": "41.478108",
        "shape_lon": "-81.699399",
        "shape_sequence": "90012"
    },
    {
        "__id": 73305,
        "shape_id": "510014",
        "shape_lat": "41.477874",
        "shape_lon": "-81.699283",
        "shape_sequence": "90013"
    },
    {
        "__id": 73306,
        "shape_id": "510014",
        "shape_lat": "41.477874",
        "shape_lon": "-81.699283",
        "shape_sequence": "100001"
    },
    {
        "__id": 73307,
        "shape_id": "510014",
        "shape_lat": "41.477700",
        "shape_lon": "-81.699197",
        "shape_sequence": "100002"
    },
    {
        "__id": 73308,
        "shape_id": "510014",
        "shape_lat": "41.477616",
        "shape_lon": "-81.699156",
        "shape_sequence": "100003"
    },
    {
        "__id": 73309,
        "shape_id": "510014",
        "shape_lat": "41.477557",
        "shape_lon": "-81.699128",
        "shape_sequence": "100004"
    },
    {
        "__id": 73310,
        "shape_id": "510014",
        "shape_lat": "41.477433",
        "shape_lon": "-81.699075",
        "shape_sequence": "100005"
    },
    {
        "__id": 73311,
        "shape_id": "510014",
        "shape_lat": "41.477306",
        "shape_lon": "-81.699038",
        "shape_sequence": "100006"
    },
    {
        "__id": 73312,
        "shape_id": "510014",
        "shape_lat": "41.477177",
        "shape_lon": "-81.699019",
        "shape_sequence": "100007"
    },
    {
        "__id": 73313,
        "shape_id": "510014",
        "shape_lat": "41.477047",
        "shape_lon": "-81.699014",
        "shape_sequence": "100008"
    },
    {
        "__id": 73314,
        "shape_id": "510014",
        "shape_lat": "41.476938",
        "shape_lon": "-81.699023",
        "shape_sequence": "100009"
    },
    {
        "__id": 73315,
        "shape_id": "510014",
        "shape_lat": "41.476716",
        "shape_lon": "-81.699045",
        "shape_sequence": "100010"
    },
    {
        "__id": 73316,
        "shape_id": "510014",
        "shape_lat": "41.475984",
        "shape_lon": "-81.699117",
        "shape_sequence": "100011"
    },
    {
        "__id": 73317,
        "shape_id": "510014",
        "shape_lat": "41.475435",
        "shape_lon": "-81.699170",
        "shape_sequence": "100012"
    },
    {
        "__id": 73318,
        "shape_id": "510014",
        "shape_lat": "41.475236",
        "shape_lon": "-81.699187",
        "shape_sequence": "100013"
    },
    {
        "__id": 73319,
        "shape_id": "510014",
        "shape_lat": "41.474901",
        "shape_lon": "-81.699220",
        "shape_sequence": "100014"
    },
    {
        "__id": 73320,
        "shape_id": "510014",
        "shape_lat": "41.474901",
        "shape_lon": "-81.699220",
        "shape_sequence": "110001"
    },
    {
        "__id": 73321,
        "shape_id": "510014",
        "shape_lat": "41.474541",
        "shape_lon": "-81.699256",
        "shape_sequence": "110002"
    },
    {
        "__id": 73322,
        "shape_id": "510014",
        "shape_lat": "41.474334",
        "shape_lon": "-81.699280",
        "shape_sequence": "110003"
    },
    {
        "__id": 73323,
        "shape_id": "510014",
        "shape_lat": "41.474213",
        "shape_lon": "-81.699291",
        "shape_sequence": "110004"
    },
    {
        "__id": 73324,
        "shape_id": "510014",
        "shape_lat": "41.474139",
        "shape_lon": "-81.699301",
        "shape_sequence": "110005"
    },
    {
        "__id": 73325,
        "shape_id": "510014",
        "shape_lat": "41.473988",
        "shape_lon": "-81.699318",
        "shape_sequence": "110006"
    },
    {
        "__id": 73326,
        "shape_id": "510014",
        "shape_lat": "41.473930",
        "shape_lon": "-81.699325",
        "shape_sequence": "110007"
    },
    {
        "__id": 73327,
        "shape_id": "510014",
        "shape_lat": "41.473717",
        "shape_lon": "-81.699347",
        "shape_sequence": "110008"
    },
    {
        "__id": 73328,
        "shape_id": "510014",
        "shape_lat": "41.473603",
        "shape_lon": "-81.699358",
        "shape_sequence": "110009"
    },
    {
        "__id": 73329,
        "shape_id": "510014",
        "shape_lat": "41.472667",
        "shape_lon": "-81.699451",
        "shape_sequence": "110010"
    },
    {
        "__id": 73330,
        "shape_id": "510014",
        "shape_lat": "41.472353",
        "shape_lon": "-81.699483",
        "shape_sequence": "110011"
    },
    {
        "__id": 73331,
        "shape_id": "510014",
        "shape_lat": "41.472353",
        "shape_lon": "-81.699483",
        "shape_sequence": "120001"
    },
    {
        "__id": 73332,
        "shape_id": "510014",
        "shape_lat": "41.472170",
        "shape_lon": "-81.699502",
        "shape_sequence": "120002"
    },
    {
        "__id": 73333,
        "shape_id": "510014",
        "shape_lat": "41.471728",
        "shape_lon": "-81.699545",
        "shape_sequence": "120003"
    },
    {
        "__id": 73334,
        "shape_id": "510014",
        "shape_lat": "41.471448",
        "shape_lon": "-81.699574",
        "shape_sequence": "120004"
    },
    {
        "__id": 73335,
        "shape_id": "510014",
        "shape_lat": "41.471237",
        "shape_lon": "-81.699594",
        "shape_sequence": "120005"
    },
    {
        "__id": 73336,
        "shape_id": "510014",
        "shape_lat": "41.471237",
        "shape_lon": "-81.699594",
        "shape_sequence": "130001"
    },
    {
        "__id": 73337,
        "shape_id": "510014",
        "shape_lat": "41.471115",
        "shape_lon": "-81.699605",
        "shape_sequence": "130002"
    },
    {
        "__id": 73338,
        "shape_id": "510014",
        "shape_lat": "41.470710",
        "shape_lon": "-81.699647",
        "shape_sequence": "130003"
    },
    {
        "__id": 73339,
        "shape_id": "510014",
        "shape_lat": "41.469913",
        "shape_lon": "-81.699734",
        "shape_sequence": "130004"
    },
    {
        "__id": 73340,
        "shape_id": "510014",
        "shape_lat": "41.469413",
        "shape_lon": "-81.699782",
        "shape_sequence": "130005"
    },
    {
        "__id": 73341,
        "shape_id": "510014",
        "shape_lat": "41.469413",
        "shape_lon": "-81.699782",
        "shape_sequence": "140001"
    },
    {
        "__id": 73342,
        "shape_id": "510014",
        "shape_lat": "41.469176",
        "shape_lon": "-81.699805",
        "shape_sequence": "140002"
    },
    {
        "__id": 73343,
        "shape_id": "510014",
        "shape_lat": "41.468983",
        "shape_lon": "-81.699828",
        "shape_sequence": "140003"
    },
    {
        "__id": 73344,
        "shape_id": "510014",
        "shape_lat": "41.468513",
        "shape_lon": "-81.699875",
        "shape_sequence": "140004"
    },
    {
        "__id": 73345,
        "shape_id": "510014",
        "shape_lat": "41.468297",
        "shape_lon": "-81.699899",
        "shape_sequence": "140005"
    },
    {
        "__id": 73346,
        "shape_id": "510014",
        "shape_lat": "41.467610",
        "shape_lon": "-81.699966",
        "shape_sequence": "140006"
    },
    {
        "__id": 73347,
        "shape_id": "510014",
        "shape_lat": "41.466965",
        "shape_lon": "-81.700032",
        "shape_sequence": "140007"
    },
    {
        "__id": 73348,
        "shape_id": "510014",
        "shape_lat": "41.466965",
        "shape_lon": "-81.700032",
        "shape_sequence": "150001"
    },
    {
        "__id": 73349,
        "shape_id": "510014",
        "shape_lat": "41.466725",
        "shape_lon": "-81.700057",
        "shape_sequence": "150002"
    },
    {
        "__id": 73350,
        "shape_id": "510014",
        "shape_lat": "41.465843",
        "shape_lon": "-81.700148",
        "shape_sequence": "150003"
    },
    {
        "__id": 73351,
        "shape_id": "510014",
        "shape_lat": "41.465843",
        "shape_lon": "-81.700148",
        "shape_sequence": "160001"
    },
    {
        "__id": 73352,
        "shape_id": "510014",
        "shape_lat": "41.465537",
        "shape_lon": "-81.700180",
        "shape_sequence": "160002"
    },
    {
        "__id": 73353,
        "shape_id": "510014",
        "shape_lat": "41.463577",
        "shape_lon": "-81.700381",
        "shape_sequence": "160003"
    },
    {
        "__id": 73354,
        "shape_id": "510014",
        "shape_lat": "41.463454",
        "shape_lon": "-81.700394",
        "shape_sequence": "160004"
    },
    {
        "__id": 73355,
        "shape_id": "510014",
        "shape_lat": "41.463248",
        "shape_lon": "-81.700414",
        "shape_sequence": "160005"
    },
    {
        "__id": 73356,
        "shape_id": "510014",
        "shape_lat": "41.463248",
        "shape_lon": "-81.700414",
        "shape_sequence": "170001"
    },
    {
        "__id": 73357,
        "shape_id": "510014",
        "shape_lat": "41.463082",
        "shape_lon": "-81.700430",
        "shape_sequence": "170002"
    },
    {
        "__id": 73358,
        "shape_id": "510014",
        "shape_lat": "41.462988",
        "shape_lon": "-81.700440",
        "shape_sequence": "170003"
    },
    {
        "__id": 73359,
        "shape_id": "510014",
        "shape_lat": "41.461876",
        "shape_lon": "-81.700557",
        "shape_sequence": "170004"
    },
    {
        "__id": 73360,
        "shape_id": "510014",
        "shape_lat": "41.461876",
        "shape_lon": "-81.700557",
        "shape_sequence": "180001"
    },
    {
        "__id": 73361,
        "shape_id": "510014",
        "shape_lat": "41.461795",
        "shape_lon": "-81.700566",
        "shape_sequence": "180002"
    },
    {
        "__id": 73362,
        "shape_id": "510014",
        "shape_lat": "41.460886",
        "shape_lon": "-81.700658",
        "shape_sequence": "180003"
    },
    {
        "__id": 73363,
        "shape_id": "510014",
        "shape_lat": "41.460116",
        "shape_lon": "-81.700740",
        "shape_sequence": "180004"
    },
    {
        "__id": 73364,
        "shape_id": "510014",
        "shape_lat": "41.460116",
        "shape_lon": "-81.700740",
        "shape_sequence": "190001"
    },
    {
        "__id": 73365,
        "shape_id": "510014",
        "shape_lat": "41.460105",
        "shape_lon": "-81.700741",
        "shape_sequence": "190002"
    },
    {
        "__id": 73366,
        "shape_id": "510014",
        "shape_lat": "41.459988",
        "shape_lon": "-81.700751",
        "shape_sequence": "190003"
    },
    {
        "__id": 73367,
        "shape_id": "510014",
        "shape_lat": "41.459535",
        "shape_lon": "-81.700792",
        "shape_sequence": "190004"
    },
    {
        "__id": 73368,
        "shape_id": "510014",
        "shape_lat": "41.459018",
        "shape_lon": "-81.700849",
        "shape_sequence": "190005"
    },
    {
        "__id": 73369,
        "shape_id": "510014",
        "shape_lat": "41.458912",
        "shape_lon": "-81.700861",
        "shape_sequence": "190006"
    },
    {
        "__id": 73370,
        "shape_id": "510014",
        "shape_lat": "41.458860",
        "shape_lon": "-81.700909",
        "shape_sequence": "190007"
    },
    {
        "__id": 73371,
        "shape_id": "510014",
        "shape_lat": "41.458785",
        "shape_lon": "-81.700923",
        "shape_sequence": "190008"
    },
    {
        "__id": 73372,
        "shape_id": "510014",
        "shape_lat": "41.458785",
        "shape_lon": "-81.700923",
        "shape_sequence": "200001"
    },
    {
        "__id": 73373,
        "shape_id": "510014",
        "shape_lat": "41.458483",
        "shape_lon": "-81.700981",
        "shape_sequence": "200002"
    },
    {
        "__id": 73374,
        "shape_id": "510014",
        "shape_lat": "41.458050",
        "shape_lon": "-81.701063",
        "shape_sequence": "200003"
    },
    {
        "__id": 73375,
        "shape_id": "510014",
        "shape_lat": "41.457961",
        "shape_lon": "-81.701077",
        "shape_sequence": "200004"
    },
    {
        "__id": 73376,
        "shape_id": "510014",
        "shape_lat": "41.457495",
        "shape_lon": "-81.701129",
        "shape_sequence": "200005"
    },
    {
        "__id": 73377,
        "shape_id": "510014",
        "shape_lat": "41.457331",
        "shape_lon": "-81.701139",
        "shape_sequence": "200006"
    },
    {
        "__id": 73378,
        "shape_id": "510014",
        "shape_lat": "41.457169",
        "shape_lon": "-81.701149",
        "shape_sequence": "200007"
    },
    {
        "__id": 73379,
        "shape_id": "510014",
        "shape_lat": "41.456936",
        "shape_lon": "-81.701153",
        "shape_sequence": "200008"
    },
    {
        "__id": 73380,
        "shape_id": "510014",
        "shape_lat": "41.456871",
        "shape_lon": "-81.701151",
        "shape_sequence": "200009"
    },
    {
        "__id": 73381,
        "shape_id": "510014",
        "shape_lat": "41.456791",
        "shape_lon": "-81.701153",
        "shape_sequence": "200010"
    },
    {
        "__id": 73382,
        "shape_id": "510014",
        "shape_lat": "41.456718",
        "shape_lon": "-81.701154",
        "shape_sequence": "200011"
    },
    {
        "__id": 73383,
        "shape_id": "510014",
        "shape_lat": "41.456568",
        "shape_lon": "-81.701162",
        "shape_sequence": "200012"
    },
    {
        "__id": 73384,
        "shape_id": "510014",
        "shape_lat": "41.456369",
        "shape_lon": "-81.701164",
        "shape_sequence": "200013"
    },
    {
        "__id": 73385,
        "shape_id": "510014",
        "shape_lat": "41.456171",
        "shape_lon": "-81.701174",
        "shape_sequence": "200014"
    },
    {
        "__id": 73386,
        "shape_id": "510014",
        "shape_lat": "41.456043",
        "shape_lon": "-81.701182",
        "shape_sequence": "200015"
    },
    {
        "__id": 73387,
        "shape_id": "510014",
        "shape_lat": "41.455459",
        "shape_lon": "-81.701246",
        "shape_sequence": "200016"
    },
    {
        "__id": 73388,
        "shape_id": "510014",
        "shape_lat": "41.455044",
        "shape_lon": "-81.701293",
        "shape_sequence": "200017"
    },
    {
        "__id": 73389,
        "shape_id": "510014",
        "shape_lat": "41.454985",
        "shape_lon": "-81.701258",
        "shape_sequence": "200018"
    },
    {
        "__id": 73390,
        "shape_id": "510014",
        "shape_lat": "41.454794",
        "shape_lon": "-81.701284",
        "shape_sequence": "200019"
    },
    {
        "__id": 73391,
        "shape_id": "510014",
        "shape_lat": "41.454718",
        "shape_lon": "-81.701292",
        "shape_sequence": "200020"
    },
    {
        "__id": 73392,
        "shape_id": "510014",
        "shape_lat": "41.454718",
        "shape_lon": "-81.701292",
        "shape_sequence": "210001"
    },
    {
        "__id": 73393,
        "shape_id": "510014",
        "shape_lat": "41.454641",
        "shape_lon": "-81.701300",
        "shape_sequence": "210002"
    },
    {
        "__id": 73394,
        "shape_id": "510014",
        "shape_lat": "41.454457",
        "shape_lon": "-81.701316",
        "shape_sequence": "210003"
    },
    {
        "__id": 73395,
        "shape_id": "510014",
        "shape_lat": "41.453827",
        "shape_lon": "-81.701377",
        "shape_sequence": "210004"
    },
    {
        "__id": 73396,
        "shape_id": "510014",
        "shape_lat": "41.453430",
        "shape_lon": "-81.701421",
        "shape_sequence": "210005"
    },
    {
        "__id": 73397,
        "shape_id": "510014",
        "shape_lat": "41.453092",
        "shape_lon": "-81.701453",
        "shape_sequence": "210006"
    },
    {
        "__id": 73398,
        "shape_id": "510014",
        "shape_lat": "41.452790",
        "shape_lon": "-81.701482",
        "shape_sequence": "210007"
    },
    {
        "__id": 73399,
        "shape_id": "510014",
        "shape_lat": "41.452790",
        "shape_lon": "-81.701482",
        "shape_sequence": "220001"
    },
    {
        "__id": 73400,
        "shape_id": "510014",
        "shape_lat": "41.452684",
        "shape_lon": "-81.701493",
        "shape_sequence": "220002"
    },
    {
        "__id": 73401,
        "shape_id": "510014",
        "shape_lat": "41.452316",
        "shape_lon": "-81.701535",
        "shape_sequence": "220003"
    },
    {
        "__id": 73402,
        "shape_id": "510014",
        "shape_lat": "41.451634",
        "shape_lon": "-81.701609",
        "shape_sequence": "220004"
    },
    {
        "__id": 73403,
        "shape_id": "510014",
        "shape_lat": "41.451485",
        "shape_lon": "-81.701626",
        "shape_sequence": "220005"
    },
    {
        "__id": 73404,
        "shape_id": "510014",
        "shape_lat": "41.451169",
        "shape_lon": "-81.701670",
        "shape_sequence": "220006"
    },
    {
        "__id": 73405,
        "shape_id": "510014",
        "shape_lat": "41.450923",
        "shape_lon": "-81.701704",
        "shape_sequence": "220007"
    },
    {
        "__id": 73406,
        "shape_id": "510014",
        "shape_lat": "41.450713",
        "shape_lon": "-81.701733",
        "shape_sequence": "220008"
    },
    {
        "__id": 73407,
        "shape_id": "510014",
        "shape_lat": "41.450461",
        "shape_lon": "-81.701774",
        "shape_sequence": "220009"
    },
    {
        "__id": 73408,
        "shape_id": "510014",
        "shape_lat": "41.450461",
        "shape_lon": "-81.701774",
        "shape_sequence": "230001"
    },
    {
        "__id": 73409,
        "shape_id": "510014",
        "shape_lat": "41.450380",
        "shape_lon": "-81.701787",
        "shape_sequence": "230002"
    },
    {
        "__id": 73410,
        "shape_id": "510014",
        "shape_lat": "41.450221",
        "shape_lon": "-81.701813",
        "shape_sequence": "230003"
    },
    {
        "__id": 73411,
        "shape_id": "510014",
        "shape_lat": "41.449970",
        "shape_lon": "-81.701854",
        "shape_sequence": "230004"
    },
    {
        "__id": 73412,
        "shape_id": "510014",
        "shape_lat": "41.449734",
        "shape_lon": "-81.701891",
        "shape_sequence": "230005"
    },
    {
        "__id": 73413,
        "shape_id": "510014",
        "shape_lat": "41.449643",
        "shape_lon": "-81.701904",
        "shape_sequence": "230006"
    },
    {
        "__id": 73414,
        "shape_id": "510014",
        "shape_lat": "41.449591",
        "shape_lon": "-81.701913",
        "shape_sequence": "230007"
    },
    {
        "__id": 73415,
        "shape_id": "510014",
        "shape_lat": "41.449259",
        "shape_lon": "-81.701970",
        "shape_sequence": "230008"
    },
    {
        "__id": 73416,
        "shape_id": "510014",
        "shape_lat": "41.448957",
        "shape_lon": "-81.702037",
        "shape_sequence": "230009"
    },
    {
        "__id": 73417,
        "shape_id": "510014",
        "shape_lat": "41.448076",
        "shape_lon": "-81.702264",
        "shape_sequence": "230010"
    },
    {
        "__id": 73418,
        "shape_id": "510014",
        "shape_lat": "41.445620",
        "shape_lon": "-81.702892",
        "shape_sequence": "230011"
    },
    {
        "__id": 73419,
        "shape_id": "510014",
        "shape_lat": "41.445227",
        "shape_lon": "-81.702984",
        "shape_sequence": "230012"
    },
    {
        "__id": 73420,
        "shape_id": "510014",
        "shape_lat": "41.444782",
        "shape_lon": "-81.703086",
        "shape_sequence": "230013"
    },
    {
        "__id": 73421,
        "shape_id": "510014",
        "shape_lat": "41.444606",
        "shape_lon": "-81.703141",
        "shape_sequence": "230014"
    },
    {
        "__id": 73422,
        "shape_id": "510014",
        "shape_lat": "41.444402",
        "shape_lon": "-81.703213",
        "shape_sequence": "230015"
    },
    {
        "__id": 73423,
        "shape_id": "510014",
        "shape_lat": "41.444081",
        "shape_lon": "-81.703391",
        "shape_sequence": "230016"
    },
    {
        "__id": 73424,
        "shape_id": "510014",
        "shape_lat": "41.443912",
        "shape_lon": "-81.703486",
        "shape_sequence": "230017"
    },
    {
        "__id": 73425,
        "shape_id": "510014",
        "shape_lat": "41.443912",
        "shape_lon": "-81.703486",
        "shape_sequence": "240001"
    },
    {
        "__id": 73426,
        "shape_id": "510014",
        "shape_lat": "41.443832",
        "shape_lon": "-81.703532",
        "shape_sequence": "240002"
    },
    {
        "__id": 73427,
        "shape_id": "510014",
        "shape_lat": "41.443512",
        "shape_lon": "-81.703727",
        "shape_sequence": "240003"
    },
    {
        "__id": 73428,
        "shape_id": "510014",
        "shape_lat": "41.443250",
        "shape_lon": "-81.703893",
        "shape_sequence": "240004"
    },
    {
        "__id": 73429,
        "shape_id": "510014",
        "shape_lat": "41.443053",
        "shape_lon": "-81.704020",
        "shape_sequence": "240005"
    },
    {
        "__id": 73430,
        "shape_id": "510014",
        "shape_lat": "41.442905",
        "shape_lon": "-81.704108",
        "shape_sequence": "240006"
    },
    {
        "__id": 73431,
        "shape_id": "510014",
        "shape_lat": "41.442670",
        "shape_lon": "-81.704256",
        "shape_sequence": "240007"
    },
    {
        "__id": 73432,
        "shape_id": "510014",
        "shape_lat": "41.442379",
        "shape_lon": "-81.704439",
        "shape_sequence": "240008"
    },
    {
        "__id": 73433,
        "shape_id": "510014",
        "shape_lat": "41.442311",
        "shape_lon": "-81.704483",
        "shape_sequence": "240009"
    },
    {
        "__id": 73434,
        "shape_id": "510014",
        "shape_lat": "41.441800",
        "shape_lon": "-81.704817",
        "shape_sequence": "240010"
    },
    {
        "__id": 73435,
        "shape_id": "510014",
        "shape_lat": "41.441800",
        "shape_lon": "-81.704817",
        "shape_sequence": "250001"
    },
    {
        "__id": 73436,
        "shape_id": "510014",
        "shape_lat": "41.441716",
        "shape_lon": "-81.704872",
        "shape_sequence": "250002"
    },
    {
        "__id": 73437,
        "shape_id": "510014",
        "shape_lat": "41.441640",
        "shape_lon": "-81.704922",
        "shape_sequence": "250003"
    },
    {
        "__id": 73438,
        "shape_id": "510014",
        "shape_lat": "41.441283",
        "shape_lon": "-81.705152",
        "shape_sequence": "250004"
    },
    {
        "__id": 73439,
        "shape_id": "510014",
        "shape_lat": "41.441147",
        "shape_lon": "-81.705241",
        "shape_sequence": "250005"
    },
    {
        "__id": 73440,
        "shape_id": "510014",
        "shape_lat": "41.441042",
        "shape_lon": "-81.705309",
        "shape_sequence": "250006"
    },
    {
        "__id": 73441,
        "shape_id": "510014",
        "shape_lat": "41.440779",
        "shape_lon": "-81.705480",
        "shape_sequence": "250007"
    },
    {
        "__id": 73442,
        "shape_id": "510014",
        "shape_lat": "41.440346",
        "shape_lon": "-81.705803",
        "shape_sequence": "250008"
    },
    {
        "__id": 73443,
        "shape_id": "510014",
        "shape_lat": "41.440234",
        "shape_lon": "-81.705899",
        "shape_sequence": "250009"
    },
    {
        "__id": 73444,
        "shape_id": "510014",
        "shape_lat": "41.440048",
        "shape_lon": "-81.706058",
        "shape_sequence": "250010"
    },
    {
        "__id": 73445,
        "shape_id": "510014",
        "shape_lat": "41.440048",
        "shape_lon": "-81.706058",
        "shape_sequence": "260001"
    },
    {
        "__id": 73446,
        "shape_id": "510014",
        "shape_lat": "41.439886",
        "shape_lon": "-81.706196",
        "shape_sequence": "260002"
    },
    {
        "__id": 73447,
        "shape_id": "510014",
        "shape_lat": "41.439444",
        "shape_lon": "-81.706556",
        "shape_sequence": "260003"
    },
    {
        "__id": 73448,
        "shape_id": "510014",
        "shape_lat": "41.439117",
        "shape_lon": "-81.706826",
        "shape_sequence": "260004"
    },
    {
        "__id": 73449,
        "shape_id": "510014",
        "shape_lat": "41.438950",
        "shape_lon": "-81.706960",
        "shape_sequence": "260005"
    },
    {
        "__id": 73450,
        "shape_id": "510014",
        "shape_lat": "41.438922",
        "shape_lon": "-81.706944",
        "shape_sequence": "260006"
    },
    {
        "__id": 73451,
        "shape_id": "510014",
        "shape_lat": "41.438814",
        "shape_lon": "-81.706929",
        "shape_sequence": "260007"
    },
    {
        "__id": 73452,
        "shape_id": "510014",
        "shape_lat": "41.437917",
        "shape_lon": "-81.706921",
        "shape_sequence": "260008"
    },
    {
        "__id": 73453,
        "shape_id": "510014",
        "shape_lat": "41.437917",
        "shape_lon": "-81.706921",
        "shape_sequence": "270001"
    },
    {
        "__id": 73454,
        "shape_id": "510014",
        "shape_lat": "41.437741",
        "shape_lon": "-81.706920",
        "shape_sequence": "270002"
    },
    {
        "__id": 73455,
        "shape_id": "510014",
        "shape_lat": "41.437019",
        "shape_lon": "-81.706915",
        "shape_sequence": "270003"
    },
    {
        "__id": 73456,
        "shape_id": "510014",
        "shape_lat": "41.436325",
        "shape_lon": "-81.706897",
        "shape_sequence": "270004"
    },
    {
        "__id": 73457,
        "shape_id": "510014",
        "shape_lat": "41.435724",
        "shape_lon": "-81.706890",
        "shape_sequence": "270005"
    },
    {
        "__id": 73458,
        "shape_id": "510014",
        "shape_lat": "41.435724",
        "shape_lon": "-81.706890",
        "shape_sequence": "280001"
    },
    {
        "__id": 73459,
        "shape_id": "510014",
        "shape_lat": "41.435589",
        "shape_lon": "-81.706889",
        "shape_sequence": "280002"
    },
    {
        "__id": 73460,
        "shape_id": "510014",
        "shape_lat": "41.435151",
        "shape_lon": "-81.706879",
        "shape_sequence": "280003"
    },
    {
        "__id": 73461,
        "shape_id": "510014",
        "shape_lat": "41.434757",
        "shape_lon": "-81.706877",
        "shape_sequence": "280004"
    },
    {
        "__id": 73462,
        "shape_id": "510014",
        "shape_lat": "41.434321",
        "shape_lon": "-81.706865",
        "shape_sequence": "280005"
    },
    {
        "__id": 73463,
        "shape_id": "510014",
        "shape_lat": "41.433927",
        "shape_lon": "-81.706855",
        "shape_sequence": "280006"
    },
    {
        "__id": 73464,
        "shape_id": "510014",
        "shape_lat": "41.433710",
        "shape_lon": "-81.706852",
        "shape_sequence": "280007"
    },
    {
        "__id": 73465,
        "shape_id": "510014",
        "shape_lat": "41.433710",
        "shape_lon": "-81.706852",
        "shape_sequence": "290001"
    },
    {
        "__id": 73466,
        "shape_id": "510014",
        "shape_lat": "41.433609",
        "shape_lon": "-81.706851",
        "shape_sequence": "290002"
    },
    {
        "__id": 73467,
        "shape_id": "510014",
        "shape_lat": "41.433162",
        "shape_lon": "-81.706844",
        "shape_sequence": "290003"
    },
    {
        "__id": 73468,
        "shape_id": "510014",
        "shape_lat": "41.432892",
        "shape_lon": "-81.706843",
        "shape_sequence": "290004"
    },
    {
        "__id": 73469,
        "shape_id": "510014",
        "shape_lat": "41.432627",
        "shape_lon": "-81.706840",
        "shape_sequence": "290005"
    },
    {
        "__id": 73470,
        "shape_id": "510014",
        "shape_lat": "41.432551",
        "shape_lon": "-81.706847",
        "shape_sequence": "290006"
    },
    {
        "__id": 73471,
        "shape_id": "510014",
        "shape_lat": "41.432508",
        "shape_lon": "-81.706854",
        "shape_sequence": "290007"
    },
    {
        "__id": 73472,
        "shape_id": "510014",
        "shape_lat": "41.432469",
        "shape_lon": "-81.706865",
        "shape_sequence": "290008"
    },
    {
        "__id": 73473,
        "shape_id": "510014",
        "shape_lat": "41.432435",
        "shape_lon": "-81.706877",
        "shape_sequence": "290009"
    },
    {
        "__id": 73474,
        "shape_id": "510014",
        "shape_lat": "41.432135",
        "shape_lon": "-81.706994",
        "shape_sequence": "290010"
    },
    {
        "__id": 73475,
        "shape_id": "510014",
        "shape_lat": "41.431829",
        "shape_lon": "-81.707117",
        "shape_sequence": "290011"
    },
    {
        "__id": 73476,
        "shape_id": "510014",
        "shape_lat": "41.431491",
        "shape_lon": "-81.707256",
        "shape_sequence": "290012"
    },
    {
        "__id": 73477,
        "shape_id": "510014",
        "shape_lat": "41.431491",
        "shape_lon": "-81.707256",
        "shape_sequence": "300001"
    },
    {
        "__id": 73478,
        "shape_id": "510014",
        "shape_lat": "41.431315",
        "shape_lon": "-81.707328",
        "shape_sequence": "300002"
    },
    {
        "__id": 73479,
        "shape_id": "510014",
        "shape_lat": "41.431126",
        "shape_lon": "-81.707401",
        "shape_sequence": "300003"
    },
    {
        "__id": 73480,
        "shape_id": "510014",
        "shape_lat": "41.430518",
        "shape_lon": "-81.707651",
        "shape_sequence": "300004"
    },
    {
        "__id": 73481,
        "shape_id": "510014",
        "shape_lat": "41.430414",
        "shape_lon": "-81.707691",
        "shape_sequence": "300005"
    },
    {
        "__id": 73482,
        "shape_id": "510014",
        "shape_lat": "41.429810",
        "shape_lon": "-81.707928",
        "shape_sequence": "300006"
    },
    {
        "__id": 73483,
        "shape_id": "510014",
        "shape_lat": "41.429810",
        "shape_lon": "-81.707928",
        "shape_sequence": "310001"
    },
    {
        "__id": 73484,
        "shape_id": "510014",
        "shape_lat": "41.429736",
        "shape_lon": "-81.707957",
        "shape_sequence": "310002"
    },
    {
        "__id": 73485,
        "shape_id": "510014",
        "shape_lat": "41.428905",
        "shape_lon": "-81.708295",
        "shape_sequence": "310003"
    },
    {
        "__id": 73486,
        "shape_id": "510014",
        "shape_lat": "41.428827",
        "shape_lon": "-81.708326",
        "shape_sequence": "310004"
    },
    {
        "__id": 73487,
        "shape_id": "510014",
        "shape_lat": "41.428478",
        "shape_lon": "-81.708466",
        "shape_sequence": "310005"
    },
    {
        "__id": 73488,
        "shape_id": "510014",
        "shape_lat": "41.428133",
        "shape_lon": "-81.708604",
        "shape_sequence": "310006"
    },
    {
        "__id": 73489,
        "shape_id": "510014",
        "shape_lat": "41.427907",
        "shape_lon": "-81.708694",
        "shape_sequence": "310007"
    },
    {
        "__id": 73490,
        "shape_id": "510014",
        "shape_lat": "41.427907",
        "shape_lon": "-81.708694",
        "shape_sequence": "320001"
    },
    {
        "__id": 73491,
        "shape_id": "510014",
        "shape_lat": "41.427467",
        "shape_lon": "-81.708871",
        "shape_sequence": "320002"
    },
    {
        "__id": 73492,
        "shape_id": "510014",
        "shape_lat": "41.427344",
        "shape_lon": "-81.708920",
        "shape_sequence": "320003"
    },
    {
        "__id": 73493,
        "shape_id": "510014",
        "shape_lat": "41.426685",
        "shape_lon": "-81.709184",
        "shape_sequence": "320004"
    },
    {
        "__id": 73494,
        "shape_id": "510014",
        "shape_lat": "41.426685",
        "shape_lon": "-81.709184",
        "shape_sequence": "330001"
    },
    {
        "__id": 73495,
        "shape_id": "510014",
        "shape_lat": "41.426598",
        "shape_lon": "-81.709219",
        "shape_sequence": "330002"
    },
    {
        "__id": 73496,
        "shape_id": "510014",
        "shape_lat": "41.425787",
        "shape_lon": "-81.709547",
        "shape_sequence": "330003"
    },
    {
        "__id": 73497,
        "shape_id": "510014",
        "shape_lat": "41.425537",
        "shape_lon": "-81.709643",
        "shape_sequence": "330004"
    },
    {
        "__id": 73498,
        "shape_id": "510014",
        "shape_lat": "41.425448",
        "shape_lon": "-81.709680",
        "shape_sequence": "330005"
    },
    {
        "__id": 73499,
        "shape_id": "510014",
        "shape_lat": "41.425318",
        "shape_lon": "-81.709728",
        "shape_sequence": "330006"
    },
    {
        "__id": 73500,
        "shape_id": "510014",
        "shape_lat": "41.425261",
        "shape_lon": "-81.709744",
        "shape_sequence": "330007"
    },
    {
        "__id": 73501,
        "shape_id": "510014",
        "shape_lat": "41.425211",
        "shape_lon": "-81.709756",
        "shape_sequence": "330008"
    },
    {
        "__id": 73502,
        "shape_id": "510014",
        "shape_lat": "41.425167",
        "shape_lon": "-81.709763",
        "shape_sequence": "330009"
    },
    {
        "__id": 73503,
        "shape_id": "510014",
        "shape_lat": "41.425084",
        "shape_lon": "-81.709772",
        "shape_sequence": "330010"
    },
    {
        "__id": 73504,
        "shape_id": "510014",
        "shape_lat": "41.425038",
        "shape_lon": "-81.709774",
        "shape_sequence": "330011"
    },
    {
        "__id": 73505,
        "shape_id": "510014",
        "shape_lat": "41.424984",
        "shape_lon": "-81.709778",
        "shape_sequence": "330012"
    },
    {
        "__id": 73506,
        "shape_id": "510014",
        "shape_lat": "41.424932",
        "shape_lon": "-81.709778",
        "shape_sequence": "330013"
    },
    {
        "__id": 73507,
        "shape_id": "510014",
        "shape_lat": "41.424867",
        "shape_lon": "-81.709779",
        "shape_sequence": "330014"
    },
    {
        "__id": 73508,
        "shape_id": "510014",
        "shape_lat": "41.424862",
        "shape_lon": "-81.709779",
        "shape_sequence": "330015"
    },
    {
        "__id": 73509,
        "shape_id": "510014",
        "shape_lat": "41.424862",
        "shape_lon": "-81.709779",
        "shape_sequence": "340001"
    },
    {
        "__id": 73510,
        "shape_id": "510014",
        "shape_lat": "41.424772",
        "shape_lon": "-81.709779",
        "shape_sequence": "340002"
    },
    {
        "__id": 73511,
        "shape_id": "510014",
        "shape_lat": "41.424361",
        "shape_lon": "-81.709781",
        "shape_sequence": "340003"
    },
    {
        "__id": 73512,
        "shape_id": "510014",
        "shape_lat": "41.424306",
        "shape_lon": "-81.709823",
        "shape_sequence": "340004"
    },
    {
        "__id": 73513,
        "shape_id": "510014",
        "shape_lat": "41.423713",
        "shape_lon": "-81.709838",
        "shape_sequence": "340005"
    },
    {
        "__id": 73514,
        "shape_id": "510014",
        "shape_lat": "41.423438",
        "shape_lon": "-81.709846",
        "shape_sequence": "340006"
    },
    {
        "__id": 73515,
        "shape_id": "510014",
        "shape_lat": "41.423438",
        "shape_lon": "-81.709846",
        "shape_sequence": "350001"
    },
    {
        "__id": 73516,
        "shape_id": "510014",
        "shape_lat": "41.423104",
        "shape_lon": "-81.709855",
        "shape_sequence": "350002"
    },
    {
        "__id": 73517,
        "shape_id": "510014",
        "shape_lat": "41.422851",
        "shape_lon": "-81.709862",
        "shape_sequence": "350003"
    },
    {
        "__id": 73518,
        "shape_id": "510014",
        "shape_lat": "41.422560",
        "shape_lon": "-81.709881",
        "shape_sequence": "350004"
    },
    {
        "__id": 73519,
        "shape_id": "510014",
        "shape_lat": "41.422029",
        "shape_lon": "-81.709900",
        "shape_sequence": "350005"
    },
    {
        "__id": 73520,
        "shape_id": "510014",
        "shape_lat": "41.421859",
        "shape_lon": "-81.709910",
        "shape_sequence": "350006"
    },
    {
        "__id": 73521,
        "shape_id": "510014",
        "shape_lat": "41.421535",
        "shape_lon": "-81.709930",
        "shape_sequence": "350007"
    },
    {
        "__id": 73522,
        "shape_id": "510014",
        "shape_lat": "41.421227",
        "shape_lon": "-81.709958",
        "shape_sequence": "350008"
    },
    {
        "__id": 73523,
        "shape_id": "510014",
        "shape_lat": "41.421024",
        "shape_lon": "-81.709981",
        "shape_sequence": "350009"
    },
    {
        "__id": 73524,
        "shape_id": "510014",
        "shape_lat": "41.420758",
        "shape_lon": "-81.710014",
        "shape_sequence": "350010"
    },
    {
        "__id": 73525,
        "shape_id": "510014",
        "shape_lat": "41.420014",
        "shape_lon": "-81.710097",
        "shape_sequence": "350011"
    },
    {
        "__id": 73526,
        "shape_id": "510014",
        "shape_lat": "41.419924",
        "shape_lon": "-81.710045",
        "shape_sequence": "350012"
    },
    {
        "__id": 73527,
        "shape_id": "510014",
        "shape_lat": "41.419724",
        "shape_lon": "-81.710076",
        "shape_sequence": "350013"
    },
    {
        "__id": 73528,
        "shape_id": "510014",
        "shape_lat": "41.419115",
        "shape_lon": "-81.710174",
        "shape_sequence": "350014"
    },
    {
        "__id": 73529,
        "shape_id": "510014",
        "shape_lat": "41.418918",
        "shape_lon": "-81.710206",
        "shape_sequence": "350015"
    },
    {
        "__id": 73530,
        "shape_id": "510014",
        "shape_lat": "41.418936",
        "shape_lon": "-81.709176",
        "shape_sequence": "350016"
    },
    {
        "__id": 73531,
        "shape_id": "510014",
        "shape_lat": "41.418972",
        "shape_lon": "-81.707170",
        "shape_sequence": "350017"
    },
    {
        "__id": 73532,
        "shape_id": "510014",
        "shape_lat": "41.418973",
        "shape_lon": "-81.707056",
        "shape_sequence": "350018"
    },
    {
        "__id": 73533,
        "shape_id": "510014",
        "shape_lat": "41.418974",
        "shape_lon": "-81.706936",
        "shape_sequence": "350019"
    },
    {
        "__id": 73534,
        "shape_id": "510014",
        "shape_lat": "41.419544",
        "shape_lon": "-81.706944",
        "shape_sequence": "350020"
    },
    {
        "__id": 73535,
        "shape_id": "510014",
        "shape_lat": "41.419601",
        "shape_lon": "-81.706915",
        "shape_sequence": "350021"
    },
    {
        "__id": 73536,
        "shape_id": "510014",
        "shape_lat": "41.419628",
        "shape_lon": "-81.706890",
        "shape_sequence": "350022"
    },
    {
        "__id": 73537,
        "shape_id": "510014",
        "shape_lat": "41.419636",
        "shape_lon": "-81.706851",
        "shape_sequence": "350023"
    },
    {
        "__id": 73538,
        "shape_id": "510014",
        "shape_lat": "41.419635",
        "shape_lon": "-81.706805",
        "shape_sequence": "350024"
    },
    {
        "__id": 73539,
        "shape_id": "510014",
        "shape_lat": "41.419630",
        "shape_lon": "-81.706768",
        "shape_sequence": "350025"
    },
    {
        "__id": 73540,
        "shape_id": "510014",
        "shape_lat": "41.419612",
        "shape_lon": "-81.706725",
        "shape_sequence": "350026"
    },
    {
        "__id": 73541,
        "shape_id": "510014",
        "shape_lat": "41.419574",
        "shape_lon": "-81.706686",
        "shape_sequence": "350027"
    },
    {
        "__id": 73542,
        "shape_id": "510014",
        "shape_lat": "41.419540",
        "shape_lon": "-81.706659",
        "shape_sequence": "350028"
    },
    {
        "__id": 73543,
        "shape_id": "510014",
        "shape_lat": "41.419482",
        "shape_lon": "-81.706656",
        "shape_sequence": "350029"
    },
    {
        "__id": 73544,
        "shape_id": "510014",
        "shape_lat": "41.419360",
        "shape_lon": "-81.706741",
        "shape_sequence": "350030"
    },
    {
        "__id": 73545,
        "shape_id": "510014",
        "shape_lat": "41.419294",
        "shape_lon": "-81.706746",
        "shape_sequence": "350031"
    },
    {
        "__id": 73546,
        "shape_id": "510014",
        "shape_lat": "41.419178",
        "shape_lon": "-81.706745",
        "shape_sequence": "350032"
    }
]